cartesius/__init__.py
cartesius/data.py
cartesius/modeling.py
cartesius/tasks.py
cartesius/tokenizers.py
cartesius/transforms.py
cartesius/utils.py
cartesius/data/testset.json
cartesius/data/valset.json
tests/__init__.py
tests/test_modeling.py
tests/test_tasks.py
tests/test_tokenizers.py
tests/test_transforms.py
spwk_cartesius-0.1.0.dist-info/METADATA
spwk_cartesius-0.1.0.dist-info/WHEEL
spwk_cartesius-0.1.0.dist-info/top_level.txt
spwk_cartesius-0.1.0.dist-info/RECORD
