Metadata-Version: 2.1
Name: spwk-cartesius
Version: 0.1.0
Summary: Benchmark & Pretraining for Cartesian coordinates feature extraction
Home-page: https://github.com/TeamSPWK/cartesius
Author: Nicolas REMOND
Author-email: remondn@spacewalk.tech
License: UNKNOWN
Platform: UNKNOWN
Classifier: Programming Language :: Python :: 3.7
Classifier: Operating System :: OS Independent
Requires-Python: >=3.7
Requires-Dist: torch (~=1.9)
Requires-Dist: pytorch-lightning (~=1.5)
Requires-Dist: shapely (~=1.8)
Requires-Dist: matplotlib (~=3.2)
Requires-Dist: wandb (~=0.12)
Provides-Extra: all
Requires-Dist: mkdocs-material (~=7.3) ; extra == 'all'
Requires-Dist: mkdocstrings (~=0.16) ; extra == 'all'
Requires-Dist: setuptools (==59.5.0) ; extra == 'all'
Requires-Dist: pytest (~=6.2) ; extra == 'all'
Requires-Dist: isort (~=5.10) ; extra == 'all'
Requires-Dist: yapf (~=0.31) ; extra == 'all'
Requires-Dist: pylint (~=2.11) ; extra == 'all'
Provides-Extra: dev
Requires-Dist: mkdocs-material (~=7.3) ; extra == 'dev'
Requires-Dist: mkdocstrings (~=0.16) ; extra == 'dev'
Requires-Dist: setuptools (==59.5.0) ; extra == 'dev'
Requires-Dist: pytest (~=6.2) ; extra == 'dev'
Requires-Dist: isort (~=5.10) ; extra == 'dev'
Requires-Dist: yapf (~=0.31) ; extra == 'dev'
Requires-Dist: pylint (~=2.11) ; extra == 'dev'
Provides-Extra: docs
Requires-Dist: mkdocs-material (~=7.3) ; extra == 'docs'
Requires-Dist: mkdocstrings (~=0.16) ; extra == 'docs'
Requires-Dist: setuptools (==59.5.0) ; extra == 'docs'
Provides-Extra: lint
Requires-Dist: isort (~=5.10) ; extra == 'lint'
Requires-Dist: yapf (~=0.31) ; extra == 'lint'
Requires-Dist: pylint (~=2.11) ; extra == 'lint'
Provides-Extra: tests
Requires-Dist: pytest (~=6.2) ; extra == 'tests'
